buildabear_jasmine7310_s_m_wang_tadelind_alw9411-0.1.6.dist-info/licenses/LICENSE
buildabearpackage/__init__.py
buildabearpackage/__main__.py
buildabearpackage/buildabear.py
buildabear_jasmine7310_s_m_wang_tadelind_alw9411-0.1.6.dist-info/METADATA
buildabear_jasmine7310_s_m_wang_tadelind_alw9411-0.1.6.dist-info/WHEEL
buildabear_jasmine7310_s_m_wang_tadelind_alw9411-0.1.6.dist-info/entry_points.txt
buildabear_jasmine7310_s_m_wang_tadelind_alw9411-0.1.6.dist-info/top_level.txt
buildabear_jasmine7310_s_m_wang_tadelind_alw9411-0.1.6.dist-info/RECORD
