Metadata-Version: 2.4
Name: buildabear_jasmine7310_s-m-wang_TadelinD_alw9411
Version: 0.1.6
Summary: A command line pet that you can feed, clean, and play with!
Author-email: Jasmine Fan <jf4654@nyu.edu>, Sophia Wang <smw9999@nyu.edu>, Tadelin De Leon <td2349@nyu.edu>, Alex Wang <alw9411@nyu.edu>
License:                     GNU GENERAL PUBLIC LICENSE
Project-URL: Homepage, https://github.com/software-students-spring2025/3-python-package-package-bear
Project-URL: Repository, https://github.com/software-students-spring2025/3-python-package-package-bear
Project-URL: Issues, https://github.com/software-students-spring2025/3-python-package-package-bear/issues
Keywords: package,bear
Classifier: Programming Language :: Python :: 3
Classifier: License :: OSI Approved :: GNU General Public License v3 (GPLv3)
Classifier: Operating System :: OS Independent
Requires-Python: >=3.8
License-File: LICENSE
Provides-Extra: dev
Requires-Dist: pytest; extra == "dev"
Dynamic: license-file
